semantic_splitter/__init__.py
semantic_splitter/splitter.py
semantic_splitter-0.1.0.dist-info/licenses/LICENSE.txt
semantic_splitter-0.1.0.dist-info/METADATA
semantic_splitter-0.1.0.dist-info/WHEEL
semantic_splitter-0.1.0.dist-info/top_level.txt
semantic_splitter-0.1.0.dist-info/RECORD
