Metadata-Version: 2.4
Name: semantic_splitter
Version: 0.1.0
Summary: Semantic chunking of documents using Sentence Transformers and LangChain,
Home-page: https://github.com/Mahemaran/semantic_splitter
Author: Maran M
Author-email: Maran M <mahemaran99@gmail.com>
License: Apache 2.0
Project-URL: Homepage, https://github.com/Mahemaran/semantic_splitter
Project-URL: Repository, https://github.com/Mahemaran/semantic_splitter
Classifier: Programming Language :: Python :: 3
Classifier: License :: OSI Approved :: Apache Software License
Classifier: Operating System :: OS Independent
Requires-Python: >=3.8
License-File: LICENSE.txt
Requires-Dist: nltk
Requires-Dist: sentence-transformers
Requires-Dist: langchain
Dynamic: author
Dynamic: home-page
Dynamic: license-file
Dynamic: requires-python
